README.md
setup.py
chinese_holidays/__init__.py
chinese_holidays/cal_chinese_holidays.py
py_chinese_holidays.egg-info/PKG-INFO
py_chinese_holidays.egg-info/SOURCES.txt
py_chinese_holidays.egg-info/dependency_links.txt
py_chinese_holidays.egg-info/top_level.txt